premium_bond_checker/__init__.py
premium_bond_checker/client.py
premium_bond_checker/exceptions.py
premium_bond_checker/models.py
premium_bond_checker/utils.py
premium_bond_checker-1.1.0.dist-info/LICENSE
premium_bond_checker-1.1.0.dist-info/METADATA
premium_bond_checker-1.1.0.dist-info/WHEEL
premium_bond_checker-1.1.0.dist-info/RECORD
