Metadata-Version: 2.3
Name: premium-bond-checker
Version: 1.1.0
Summary: Simple premium bond checker library
License: MIT
Author: Malachi Soord
Author-email: inverse.chi@gmail.com
Requires-Python: >=3.10,<4.0
Classifier: License :: OSI Approved :: MIT License
Classifier: Programming Language :: Python :: 3
Classifier: Programming Language :: Python :: 3.10
Classifier: Programming Language :: Python :: 3.11
Classifier: Programming Language :: Python :: 3.12
Classifier: Programming Language :: Python :: 3.13
Requires-Dist: holidays (>=0.71,<=1.0)
Requires-Dist: pytz (>=2024.2,<2026.0)
Requires-Dist: requests (>=2.31.0,<3.0.0)
